setup.py
nginx_signing/__init__.py
nginx_signing/signing.py
nginx_signing.egg-info/PKG-INFO
nginx_signing.egg-info/SOURCES.txt
nginx_signing.egg-info/dependency_links.txt
nginx_signing.egg-info/top_level.txt