Metadata-Version: 1.0
Name: nginx-signing
Version: 0.1.5
Summary: Signs urls to work with the nginx Secure Link module
Home-page: http://github.com/gjcourt/python-nginx-signer
Author: George Courtsunis
Author-email: gjcourt@gmail.com
License: MIT License
Keywords: nginx signing secure_link
Platform: UNKNOWN
